automateui/__init__.py
automateui-0.0.1.dev0.dist-info/WHEEL
automateui-0.0.1.dev0.dist-info/METADATA
automateui-0.0.1.dev0.dist-info/RECORD
